LICENSE.txt
MANIFEST.in
README.md
VERSION.txt
setup.py
src/main.py
src/WebResources/__init__.py
src/WebResources/webWorker.py
src/core/__init__.py
src/core/helper.py
src/core/pandas_module.py
venv/Lib/site-packages/easy_install.py
venv/Lib/site-packages/jdcal.py
venv/Lib/site-packages/six.py
venv/Lib/site-packages/dateutil/__init__.py
venv/Lib/site-packages/dateutil/_common.py
venv/Lib/site-packages/dateutil/_version.py
venv/Lib/site-packages/dateutil/easter.py
venv/Lib/site-packages/dateutil/relativedelta.py
venv/Lib/site-packages/dateutil/rrule.py
venv/Lib/site-packages/dateutil/tzwin.py
venv/Lib/site-packages/dateutil/utils.py
venv/Lib/site-packages/dateutil/parser/__init__.py
venv/Lib/site-packages/dateutil/parser/_parser.py
venv/Lib/site-packages/dateutil/parser/isoparser.py
venv/Lib/site-packages/dateutil/tz/__init__.py
venv/Lib/site-packages/dateutil/tz/_common.py
venv/Lib/site-packages/dateutil/tz/_factories.py
venv/Lib/site-packages/dateutil/tz/tz.py
venv/Lib/site-packages/dateutil/tz/win.py
venv/Lib/site-packages/dateutil/zoneinfo/__init__.py
venv/Lib/site-packages/dateutil/zoneinfo/rebuild.py
venv/Lib/site-packages/et_xmlfile/__init__.py
venv/Lib/site-packages/et_xmlfile/xmlfile.py
venv/Lib/site-packages/et_xmlfile-1.0.1-py3.9.egg-info/SOURCES.txt
venv/Lib/site-packages/et_xmlfile-1.0.1-py3.9.egg-info/dependency_links.txt
venv/Lib/site-packages/et_xmlfile-1.0.1-py3.9.egg-info/installed-files.txt
venv/Lib/site-packages/et_xmlfile-1.0.1-py3.9.egg-info/top_level.txt
venv/Lib/site-packages/et_xmlfile/tests/__init__.py
venv/Lib/site-packages/et_xmlfile/tests/common_imports.py
venv/Lib/site-packages/et_xmlfile/tests/helper.py
venv/Lib/site-packages/et_xmlfile/tests/test_incremental_xmlfile.py
venv/Lib/site-packages/jdcal-1.4.1.dist-info/LICENSE.txt
venv/Lib/site-packages/jdcal-1.4.1.dist-info/top_level.txt
venv/Lib/site-packages/numpy/LICENSE.txt
venv/Lib/site-packages/numpy/__config__.py
venv/Lib/site-packages/numpy/__init__.py
venv/Lib/site-packages/numpy/_distributor_init.py
venv/Lib/site-packages/numpy/_globals.py
venv/Lib/site-packages/numpy/_pytesttester.py
venv/Lib/site-packages/numpy/conftest.py
venv/Lib/site-packages/numpy/ctypeslib.py
venv/Lib/site-packages/numpy/dual.py
venv/Lib/site-packages/numpy/matlib.py
venv/Lib/site-packages/numpy/setup.py
venv/Lib/site-packages/numpy/version.py
venv/Lib/site-packages/numpy-1.20.1.dist-info/LICENSE.txt
venv/Lib/site-packages/numpy-1.20.1.dist-info/LICENSES_bundled.txt
venv/Lib/site-packages/numpy-1.20.1.dist-info/entry_points.txt
venv/Lib/site-packages/numpy-1.20.1.dist-info/top_level.txt
venv/Lib/site-packages/numpy/compat/__init__.py
venv/Lib/site-packages/openpyxl-3.0.6.dist-info/top_level.txt
venv/Lib/site-packages/pandas-1.2.2.dist-info/entry_points.txt
venv/Lib/site-packages/pandas-1.2.2.dist-info/top_level.txt
venv/Lib/site-packages/pip-20.2.3.dist-info/LICENSE.txt
venv/Lib/site-packages/pip-20.2.3.dist-info/entry_points.txt
venv/Lib/site-packages/pip-20.2.3.dist-info/top_level.txt
venv/Lib/site-packages/python_dateutil-2.8.1.dist-info/top_level.txt
venv/Lib/site-packages/pytz-2021.1.dist-info/LICENSE.txt
venv/Lib/site-packages/pytz-2021.1.dist-info/top_level.txt
venv/Lib/site-packages/selenium-3.141.0.dist-info/top_level.txt
venv/Lib/site-packages/setuptools-49.2.1.dist-info/dependency_links.txt
venv/Lib/site-packages/setuptools-49.2.1.dist-info/entry_points.txt
venv/Lib/site-packages/setuptools-49.2.1.dist-info/top_level.txt
venv/Lib/site-packages/six-1.15.0.dist-info/top_level.txt
venv/Lib/site-packages/urllib3-1.26.3.dist-info/LICENSE.txt
venv/Lib/site-packages/urllib3-1.26.3.dist-info/top_level.txt
webMole.egg-info/PKG-INFO
webMole.egg-info/SOURCES.txt
webMole.egg-info/dependency_links.txt
webMole.egg-info/requires.txt
webMole.egg-info/top_level.txt